regula/__init__.py
regula/facesdk/__init__.py
regula/facesdk/webclient/__init__.py
regula/facesdk/webclient/ext/__init__.py
regula/facesdk/webclient/ext/common.py
regula/facesdk/webclient/ext/api/__init__.py
regula/facesdk/webclient/ext/api/group_api.py
regula/facesdk/webclient/ext/api/matching_api.py
regula/facesdk/webclient/ext/api/person_api.py
regula/facesdk/webclient/ext/api/sdk.py
regula/facesdk/webclient/ext/api/search_api.py
regula/facesdk/webclient/ext/models/__init__.py
regula/facesdk/webclient/ext/models/detect_request.py
regula/facesdk/webclient/ext/models/match_image.py
regula/facesdk/webclient/ext/models/match_request.py
regula/facesdk/webclient/gen/__init__.py
regula/facesdk/webclient/gen/api_client.py
regula/facesdk/webclient/gen/configuration.py
regula/facesdk/webclient/gen/exceptions.py
regula/facesdk/webclient/gen/model_utils.py
regula/facesdk/webclient/gen/rest.py
regula/facesdk/webclient/gen/api/__init__.py
regula/facesdk/webclient/gen/api/diagnostics_api.py
regula/facesdk/webclient/gen/api/group_api.py
regula/facesdk/webclient/gen/api/liveness_2_0_api.py
regula/facesdk/webclient/gen/api/liveness_api.py
regula/facesdk/webclient/gen/api/matching_api.py
regula/facesdk/webclient/gen/api/person_api.py
regula/facesdk/webclient/gen/api/search_api.py
regula/facesdk/webclient/gen/apis/__init__.py
regula/facesdk/webclient/gen/model/__init__.py
regula/facesdk/webclient/gen/model/add_image_to_person_request.py
regula/facesdk/webclient/gen/model/add_image_to_person_request_image.py
regula/facesdk/webclient/gen/model/add_image_to_person_response.py
regula/facesdk/webclient/gen/model/attribute_config.py
regula/facesdk/webclient/gen/model/attribute_config_list.py
regula/facesdk/webclient/gen/model/crop.py
regula/facesdk/webclient/gen/model/detect_request.py
regula/facesdk/webclient/gen/model/detect_request_attributes.py
regula/facesdk/webclient/gen/model/detect_response.py
regula/facesdk/webclient/gen/model/detect_response_all_of.py
regula.facesdk.webclient-7.4.33.dist-info/METADATA
regula.facesdk.webclient-7.4.33.dist-info/WHEEL
regula.facesdk.webclient-7.4.33.dist-info/top_level.txt
regula.facesdk.webclient-7.4.33.dist-info/RECORD
