Metadata-Version: 2.1
Name: regula.facesdk.webclient
Version: 7.4.33
Summary: Regula's FaceSDK web python client
Home-page: https://regulaforensics.com
Author: Regula Forensics, Inc.
Author-email: support@regulaforensics.com
Keywords: face recognition,facesdk,regulaforensics,regula
Requires-Python: >=3.5
Requires-Dist: certifi>=2024.07.04
Requires-Dist: six>=1.10
Requires-Dist: python-dateutil>=2.5.3
Requires-Dist: urllib3>=2.2.2
Requires-Dist: vistir<=0.6.1,>=0.4.0
Requires-Dist: idna==3.7
Requires-Dist: requests>=2.32.3
